[{"name":"대학 선배","maxHp":325,"hp":325,"exp":22,"str":67,"def":9,"description":"그녀의 대학 선배가 등장했다. \"오빠가~\"","id":0},{"name":"중학교 동창","maxHp":465,"hp":465,"exp":24,"str":95,"def":5,"description":"그녀의 중학교 동창이 등장했다.","id":1},{"name":"전 애인","maxHp":5,"hp":5,"exp":21,"str":3,"def":10,"description":"그녀의 전 애인이 등장했다. 헉..","id":2},{"name":"첫사랑","maxHp":130,"hp":130,"exp":35,"str":28,"def":8,"description":"그녀의 첫사랑이 등장했다. 이런...","id":3},{"name":"그녀의 과제","maxHp":410,"hp":410,"exp":21,"str":84,"def":1,"description":"그녀의 과제가 등장했다. 좀 많은가..?","id":4},{"name":"인관심 조원","maxHp":110,"hp":110,"exp":31,"str":24,"def":8,"description":"그녀의 인관심 조원이 등장했다.","id":5}]